<annotation>
	<folder>KC</folder>
	<filename>KC10.jpg</filename>
	<path>G:\Playing Card Dataset\Images\KC\KC10.jpg</path>
	<source>
		<database>Unknown</database>
	</source>
	<size>
		<width>4608</width>
		<height>3456</height>
		<depth>3</depth>
	</size>
	<segmented>0</segmented>
	<object>
		<name>KC</name>
		<pose>Unspecified</pose>
		<truncated>0</truncated>
		<difficult>0</difficult>
		<bndbox>
			<xmin>1198</xmin>
			<ymin>1246</ymin>
			<xmax>1568</xmax>
			<ymax>1579</ymax>
		</bndbox>
	</object>
</annotation>
